{"texteDecisionIntegre":"FACTICE","metadonnees":{"idDecision":"0605_2024L00074_2024-01-26_5","idGroupement":"01","idJuridiction":"0605","libelleJuridiction":"NICE","dateDecision":"20240126","numeroDossier":"2024L00074","idChambre":"09","libelleChambre":"Chambre du conseil ouvertures PCL","idMatiere":"251_4","libelleMatiere":"Demande rectification matérielle art 462","idProcedure":"L","libelleProcedure":"CONTENTIEUX LIE","decisionPublique":true,"debatChambreDuConseil":false,"interetParticulier":false,"composition":[],"parties":[],"occultationsComplementaires":{"personneMorale":false,"personnePhysicoMoraleGeoMorale":false,"adresse":false,"dateCivile":false,"plaqueImmatriculation":false,"cadastre":false,"chaineNumeroIdentifiante":false,"coordonneeElectronique":false,"professionnelMagistratGreffier":false,"motifsDebatsChambreConseil":false,"motifsSecretAffaires":false,"conserverElement":null,"supprimerElement":null}},"date":"2025-02-18T17:00:59.000Z"}